{
  "grundforfattningId": 62518,
  "previousId": 61820,
  "beteckning": "2015:1053",
  "beteckningSortable": "2015:1053",
  "publiceringsar": "2015",
  "lopnummer": "1053",
  "rubrik": "Förordning (2015:1053) om totalförsvar och höjd beredskap",
  "tidsbegransadDateTime": null,
  "upphavdDateTime": null,
  "upphavdOvergangsbestammelse": false,
  "upphavdDenDagenRegeringenBestammer": false,
  "ikraftDateTime": "2016-04-01T00:00:00",
  "ikraftOvergangsbestammelse": false,
  "ikraftDenDagenRegeringenBestammer": false,
  "notis": false,
  "organisation": {
    "organisationId": 0,
    "namn": "Försvarsdepartementet",
    "enhet": null,
    "namnOchEnhet": "Försvarsdepartementet",
    "departementId": 4,
    "myndighetId": null
  },
  "forfattningstypNamn": "Förordning",
  "register": {
    "registerInformationId": 62515,
    "forarbeten": null,
    "eUdirektiv": false,
    "forfattningssamling": null,
    "celexnummer": null,
    "taggar": "höjd beredskap,totalförsvar",
    "overgangsbestammelserVidTidsbegransning": null,
    "skapadDateTime": "2026-01-02T15:07:35.2133463",
    "uppdateradDateTime": "2026-01-02T15:08:15.9587026",
    "utkastId": null,
    "publicerad": true,
    "publiceradDateTime": "2026-01-02T15:08:15.9587024",
    "arkiverad": false,
    "historisk": false,
    "utkast": false
  },
  "fulltext": {
    "fulltextInformationId": 85338,
    "upphavdGenom": null,
    "andringInford": "t.o.m. SFS 2025:1145",
    "omtryck": null,
    "utfardadDateTime": "2015-12-17T00:00:00",
    "ovrigt": null,
    "forfattningstext": "Inledande bestämmelser\r\n\r\n1 § Denna förordning ansluter till vad som föreskrivs i lagen \r\n(1992:1403) om totalförsvar och höjd beredskap.\r\n\r\nFörordningen innehåller bestämmelser om \r\n\r\n- hur höjd beredskap tillkännages, vilka författningar som då \r\nomedelbart ska tillämpas och åtgärder som då ska genomföras, \r\n\r\n- underlag till Försvarsmakten, och \r\n\r\n- säkra kryptografiska funktioner.\r\nFörordning (2022:563).\r\n\r\n2 § I lagen (2006:544) om kommuners och regioners åtgärder \r\ninför och vid extraordinära händelser i fredstid och höjd \r\nberedskap och förordningen (2006:637) om kommuners och \r\nregioners åtgärder inför och vid extraordinära händelser i \r\nfredstid och höjd beredskap finns bestämmelser om vilka \r\nåtgärder som kommuner och regioner ska vidta vid höjd \r\nberedskap.\r\n\r\nI förordningen (2022:524) om statliga myndigheters beredskap \r\nfinns bestämmelser om uppgifter som statliga myndigheter under \r\nregeringen har inför och vid fredstida krissituationer och \r\nhöjd beredskap. För länsstyrelserna finns även bestämmelser i \r\nförordningen (2017:870) om länsstyrelsernas krisberedskap och \r\nuppgifter inför och vid höjd beredskap och i förordningen \r\n(2022:525) om civilområdesansvariga länsstyrelser. \r\n\r\nBestämmelserna i denna förordning ska tillämpas bara om något \r\nannat inte följer av lag eller annan förordning.\r\nFörordning (2022:563).\r\n\r\n3 § Bestämmelserna i 18 och 19 §§ gäller för statliga \r\nmyndigheter under regeringen med undantag av \r\nRegeringskansliet, kommittéväsendet och Försvarsmakten. För \r\nutlandsmyndigheterna tillämpas bestämmelserna endast i den \r\nutsträckning som bestäms i föreskrifter som meddelas av \r\nRegeringskansliet (Utrikesdepartementet). \r\nFörordning (2022:563).\r\n\r\nUnderlag till Försvarsmakten\r\n\r\n4 § Har upphävts genom förordning (2022:563).\r\n\r\n5 § Har upphävts genom förordning (2022:563).\r\n\r\n6 § Har upphävts genom förordning (2022:563).\r\n\r\n7 § Försvarets materielverk, Försvarets radioanstalt, \r\nTotalförsvarets forskningsinstitut, Totalförsvarets plikt- och \r\nprövningsverk, Fortifikationsverket och Försvarshögskolan ska \r\ninför och vid höjd beredskap lämna Försvarsmakten det underlag \r\nsom behövs för att myndigheten ska kunna fullgöra sin \r\ninformationsskyldighet till regeringen. Förordning (2022:563).\r\n\r\n8 § Beredskapsmyndigheter och sektorsansvariga myndigheter \r\nenligt förordningen (2022:524) om statliga myndigheters \r\nberedskap ska inför och vid höjd beredskap lämna \r\nFörsvarsmakten det underlag som behövs för att myndigheten ska \r\nkunna fullgöra sin informationsskyldighet till regeringen. \r\nMotsvarande underlag ska lämnas till Försvarsmakten av de \r\nlänsstyrelser som är civilområdesansvariga enligt 7 a § \r\nförordningen (2017:868) med länsstyrelseinstruktion.\r\nFörordning (2022:563).\r\n\r\nHur beslut om höjd beredskap tillkännages\r\n\r\n9 § Att beredskapen i Sverige höjts till skärpt eller högsta \r\nberedskap tillkännages, förutom på det sätt som föreskrivs i \r\n4 § lagen (1976:633) om kungörande av lagar och andra \r\nförfattningar, i ljudradion och televisionen. Om det råder \r\nhögsta beredskap i hela landet, kan regeringen besluta att \r\ndetta ska tillkännages även genom beredskapslarm.\r\n\r\n10 § Beredskapslarm ges på anläggningar för utomhusalarmering \r\ngenom trettio sekunder långa signaler med femton sekunders \r\nuppehåll mellan signalerna under sammanlagt fem minuter.\r\n\r\nÅtgärder vid höjd beredskap\r\n\r\n11 § När beredskapen höjts, ska Försvarsmakten \r\nkrigsorganiseras i den omfattning som regeringen bestämmer. \r\nVid beredskapslarm ska hela Försvarsmakten \r\nkrigsorganiseras.\r\n\r\n12 § Vid högsta beredskap ska kommuner och regioner övergå \r\ntill krigsorganisation. \r\n\r\nVid beredskapslarm ska kommuner och regioner samt de \r\ntrossamfund och andra enskilda organisationer och de \r\nnäringsidkare som enligt överenskommelse eller på annan grund \r\när skyldiga att fortsätta sin verksamhet i krig övergå till \r\nkrigsorganisation. Förordning (2019:1114).\r\n\r\n13 § Vid beredskapslarm ska följande författningar omedelbart \r\ntillämpas i sin helhet:\r\n\r\n- lagen (1939:299) om förbud i vissa fall mot överlåtelse \r\neller upplåtelse av fartyg m.m.,\r\n\r\n- lagen (1940:176) med vissa bestämmelser om fraktfart med \r\nsvenska fartyg,\r\n\r\n- lagen (1957:684) om betalningsväsendet under \r\nkrigsförhållanden,\r\n\r\n- kungörelsen (1960:516) med tillämpningsföreskrifter till \r\nlagen (1940:176) med vissa bestämmelser om fraktfart med \r\nsvenska fartyg,\r\n\r\n- lagen (1962:627) om utnyttjande av vattenkraft vid krig,\r\n\r\n- krigshandelslagen (1964:19),\r\n\r\n- förfogandelagen (1978:262),\r\n\r\n- ransoneringslagen (1978:268),\r\n\r\n- lagen (1979:1088) om gränsövervakningen i krig m.m.,\r\n\r\n- arbetsrättsliga beredskapslagen (1987:1262),\r\n\r\n- lagen (1988:97) om förfarandet hos kommunerna, \r\nförvaltningsmyndigheterna och domstolarna under krig eller \r\nkrigsfara m.m.,\r\n\r\n- prisregleringslagen (1989:978),\r\n\r\n- förordningen (1991:1195) om skolväsendet under krig och vid \r\nkrigsfara m.m.,\r\n\r\n- förordningen (1991:1269) om verksamheten vid statliga skolor \r\nunder krig och vid krigsfara,\r\n\r\n- lagen (1992:1402) om undanförsel och förstöring,\r\n\r\n- lagen (1994:2077) om arbetsförmedlingstvång,\r\n\r\n- lagen (1995:439) om beskattning, förtullning och \r\nfolkbokföring under krig eller krigsfara m.m., och\r\n\r\n- lagen (1999:890) om försäkringsverksamhet under krig eller \r\nkrigsfara m.m.\r\n\r\nBeredskapslarm medför vidare att 6-11 §§ förordningen \r\n(2017:870) om länsstyrelsernas krisberedskap och uppgifter \r\ninför och vid höjd beredskap och 10-12 §§ förordningen \r\n(2022:525) om civilområdesansvariga länsstyrelser omedelbart \r\nska tillämpas. Förordning (2022:563).\r\n\r\n14 § Beredskapslarm innebär föreskrift om allmän tjänsteplikt \r\nenligt 6 kap. 1 § lagen (1994:1809) om totalförsvarsplikt.\r\n\r\nBeredskapslarm innebär vidare föreskrift enligt 1 § \r\nförordningen (1982:314) om utnyttjande av Kustbevakningen \r\ninom Försvarsmakten.\r\n\r\nBeredskapslarm innebär även förordnande enligt 2 § lagen \r\n(1940:176) med vissa bestämmelser om fraktfart med svenska \r\nfartyg samt förordnande enligt 4 kap. 1 § \r\nsjötrafikförordningen (1986:300).\r\n\r\n15 § Beredskapslarm innebär order till den som är \r\nkrigsplacerad inom totalförsvaret enligt lagen (1994:1809) om \r\ntotalförsvarsplikt eller på annan grund att omedelbart \r\ninställa sig till tjänstgöring enligt krigsplaceringsorder \r\neller motsvarande handling. Beredskapslarm innebär också att \r\negendom som tagits ut i fredstid med stöd av förordningen \r\n(1992:391) om uttagning av egendom för totalförsvarets behov \r\nomedelbart ska tillhandahållas i enlighet med tidigare \r\nlämnade uttagningsbesked.\r\n\r\nSäkra kryptografiska funktioner\r\n\r\n16 § Regeringskansliet, Polismyndigheten, Säkerhetspolisen, \r\nMyndigheten för civilt försvar, Kustbevakningen, Myndigheten \r\nför psykologiskt försvar, Försvarsmakten, Försvarets \r\nmaterielverk, Försvarets radioanstalt, Totalförsvarets \r\nforskningsinstitut, Totalförsvarets plikt- och prövningsverk, \r\nMyndigheten för totalförsvarsanalys, Fortifikationsverket och \r\nFörsvarshögskolan ska ha säkra kryptografiska funktioner. I \r\ndenna förordning används uttrycket säkra kryptografiska \r\nfunktioner i betydelsen kryptografiska funktioner godkända av \r\nFörsvarsmakten.\r\n\r\nMyndigheten för civilt försvar beslutar vilka övriga \r\nmyndigheter som ska ha säkra kryptografiska funktioner.\r\n\r\nMyndigheten för civilt försvar beslutar även vilka företag som \r\nefter överenskommelse ska få tillgång till säkra \r\nkryptografiska funktioner. Myndigheten för civilt försvar får \r\ndärutöver ingå avtal om tilldelning med kommuner och \r\norganisationer som har behov av säkra kryptografiska \r\nfunktioner. Förordning (2025:1145).\r\n\r\n17 § Försvarsmakten svarar för att Försvarsmakten, Försvarets \r\nmaterielverk, Totalförsvarets forskningsinstitut, \r\nTotalförsvarets plikt- och prövningsverk, Fortifikationsverket \r\noch Försvarshögskolan tilldelas säkra kryptografiska \r\nfunktioner. Försvarets radioanstalt svarar för att övriga som \r\nenligt 16 § ska ha säkra kryptografiska funktioner tilldelas \r\nsådana. Förordning (2020:1289).\r\n\r\n18 § Myndigheter som tilldelats säkra kryptografiska \r\nfunktioner ska under normal kontorstid kunna ta emot och sända \r\nkrypterade meddelanden.\r\n\r\nVid fredstida krissituationer och höjd beredskap ska \r\nmyndigheterna kunna ta emot och sända krypterade meddelanden \r\näven under icke kontorstid.\r\n\r\nMyndigheten för civilt försvar, eller annars, efter samråd med \r\nMyndigheten för civilt försvar, en annan myndighet som har \r\nbehov av information, ska ingå överenskommelse med ett sådant \r\nföretag, en sådan kommun eller organisation som tilldelats \r\nsystem med stöd av 16 § tredje stycket om när krypterade \r\nmeddelanden ska kunna tas emot och sändas. \r\nFörordning (2025:1145).\r\n\r\nVerkställighetsföreskrifter\r\n\r\n19 § Myndigheten för civilt försvar får meddela de ytterligare \r\nföreskrifter som behövs för verkställigheten av 18 §, utom i \r\nfråga om Kustbevakningen, Försvarets materielverk, Försvarets \r\nradioanstalt, Totalförsvarets forskningsinstitut, Myndigheten \r\nför totalförsvarsanalys, Fortifikationsverket och \r\nFörsvarshögskolan. Förordning (2025:1145).\r\n\r\n20 § Försvarsmakten får meddela de ytterligare föreskrifter \r\nsom behövs för verkställigheten av 7 och 8 §§. \r\nFörordning (2022:563).",
    "skapadDateTime": "2026-01-02T15:07:35.2133459",
    "uppdateradDateTime": "2026-01-02T15:08:15.9587179",
    "utkastId": null,
    "publicerad": true,
    "publiceradDateTime": "2026-01-02T15:08:15.9587178",
    "arkiverad": false,
    "historisk": false,
    "utkast": false
  },
  "andringsforfattningar": [
    {
      "andringsforfattningId": 647678,
      "beteckning": "2022:1770",
      "anteckningar": "ändr. 16, 19 §§",
      "ikraftDateTime": "2023-01-01T00:00:00",
      "ikraftOvergangsbestammelse": false,
      "ikraftDenDagenRegeringenBestammer": false,
      "forarbeten": null,
      "rubrik": "Förordning (2022:1770) om ändring i förordningen (2015:1053) om totalförsvar och höjd beredskap",
      "lopnummer": "1770",
      "celexnummer": null,
      "bihangsuppgifterTillAldreGrundforfattningar": null,
      "publiceringsar": "2022",
      "eUdirektiv": false,
      "skapadDateTime": "2026-01-02T15:07:35.2285277",
      "uppdateradDateTime": "2026-01-02T15:08:15.9587778",
      "utkastId": null,
      "publicerad": true,
      "borttagen": false,
      "publiceradDateTime": "2026-01-02T15:08:15.9587776",
      "arkiverad": false,
      "historisk": false,
      "utkast": false
    },
    {
      "andringsforfattningId": 647679,
      "beteckning": "2022:563",
      "anteckningar": "upph. 4, 5, 6 §§, rubr. närmast före 4, 7 §§; ändr. 1, 2, 3, 7, 8, 13, 18, 19 §§, rubr. närmast efter 3 §; ny 20 §",
      "ikraftDateTime": "2022-10-01T00:00:00",
      "ikraftOvergangsbestammelse": false,
      "ikraftDenDagenRegeringenBestammer": false,
      "forarbeten": null,
      "rubrik": "Förordning (2022:563) om ändring i förordningen (2015:1053) om totalförsvar och höjd beredskap",
      "lopnummer": "563",
      "celexnummer": null,
      "bihangsuppgifterTillAldreGrundforfattningar": null,
      "publiceringsar": "2022",
      "eUdirektiv": false,
      "skapadDateTime": "2026-01-02T15:07:35.228528",
      "uppdateradDateTime": "2026-01-02T15:08:15.9588004",
      "utkastId": null,
      "publicerad": true,
      "borttagen": false,
      "publiceradDateTime": "2026-01-02T15:08:15.9588003",
      "arkiverad": false,
      "historisk": false,
      "utkast": false
    },
    {
      "andringsforfattningId": 647680,
      "beteckning": "2021:935",
      "anteckningar": "ändr. 16 §",
      "ikraftDateTime": "2022-01-01T00:00:00",
      "ikraftOvergangsbestammelse": false,
      "ikraftDenDagenRegeringenBestammer": false,
      "forarbeten": null,
      "rubrik": "Förordning (2021:935) om ändring i förordningen (2015:1053) om totalförsvar och höjd beredskap",
      "lopnummer": "935",
      "celexnummer": null,
      "bihangsuppgifterTillAldreGrundforfattningar": null,
      "publiceringsar": "2021",
      "eUdirektiv": false,
      "skapadDateTime": "2026-01-02T15:07:35.2285282",
      "uppdateradDateTime": "2026-01-02T15:08:15.95881",
      "utkastId": null,
      "publicerad": true,
      "borttagen": false,
      "publiceradDateTime": "2026-01-02T15:08:15.9588099",
      "arkiverad": false,
      "historisk": false,
      "utkast": false
    },
    {
      "andringsforfattningId": 647681,
      "beteckning": "2020:1289",
      "anteckningar": "ändr. 7, 16, 17 §§",
      "ikraftDateTime": "2021-02-01T00:00:00",
      "ikraftOvergangsbestammelse": false,
      "ikraftDenDagenRegeringenBestammer": false,
      "forarbeten": null,
      "rubrik": "Förordning (2020:1289) om ändring i förordningen (2015:1053) om totalförsvar och höjd beredskap",
      "lopnummer": "1289",
      "celexnummer": null,
      "bihangsuppgifterTillAldreGrundforfattningar": null,
      "publiceringsar": "2020",
      "eUdirektiv": false,
      "skapadDateTime": "2026-01-02T15:07:35.2285285",
      "uppdateradDateTime": "2026-01-02T15:08:15.9588235",
      "utkastId": null,
      "publicerad": true,
      "borttagen": false,
      "publiceradDateTime": "2026-01-02T15:08:15.9588234",
      "arkiverad": false,
      "historisk": false,
      "utkast": false
    },
    {
      "andringsforfattningId": 647682,
      "beteckning": "2019:1114",
      "anteckningar": "ändr. 2, 4, 12 §§",
      "ikraftDateTime": "2020-01-01T00:00:00",
      "ikraftOvergangsbestammelse": false,
      "ikraftDenDagenRegeringenBestammer": false,
      "forarbeten": null,
      "rubrik": "Förordning (2019:1114) om ändring i förordningen (2015:1053) om totalförsvar och höjd beredskap",
      "lopnummer": "1114",
      "celexnummer": null,
      "bihangsuppgifterTillAldreGrundforfattningar": null,
      "publiceringsar": "2019",
      "eUdirektiv": false,
      "skapadDateTime": "2026-01-02T15:07:35.2285288",
      "uppdateradDateTime": "2026-01-02T15:08:15.9588309",
      "utkastId": null,
      "publicerad": true,
      "borttagen": false,
      "publiceradDateTime": "2026-01-02T15:08:15.9588308",
      "arkiverad": false,
      "historisk": false,
      "utkast": false
    },
    {
      "andringsforfattningId": 647683,
      "beteckning": "2019:6",
      "anteckningar": "ändr. 13 §",
      "ikraftDateTime": "2019-02-01T00:00:00",
      "ikraftOvergangsbestammelse": false,
      "ikraftDenDagenRegeringenBestammer": false,
      "forarbeten": null,
      "rubrik": "Förordning (2019:6) om ändring i förordningen (2015:1053) om totalförsvar och höjd beredskap",
      "lopnummer": "6",
      "celexnummer": null,
      "bihangsuppgifterTillAldreGrundforfattningar": null,
      "publiceringsar": "2019",
      "eUdirektiv": false,
      "skapadDateTime": "2026-01-02T15:07:35.2285291",
      "uppdateradDateTime": "2026-01-02T15:08:15.9588368",
      "utkastId": null,
      "publicerad": true,
      "borttagen": false,
      "publiceradDateTime": "2026-01-02T15:08:15.9588367",
      "arkiverad": false,
      "historisk": false,
      "utkast": false
    },
    {
      "andringsforfattningId": 647684,
      "beteckning": "2017:879",
      "anteckningar": "ändr. 13 §",
      "ikraftDateTime": "2017-11-01T00:00:00",
      "ikraftOvergangsbestammelse": false,
      "ikraftDenDagenRegeringenBestammer": false,
      "forarbeten": null,
      "rubrik": "Förordning (2017:879) om ändring i förordningen (2015:1053) om totalförsvar och höjd beredskap",
      "lopnummer": "879",
      "celexnummer": null,
      "bihangsuppgifterTillAldreGrundforfattningar": null,
      "publiceringsar": "2017",
      "eUdirektiv": false,
      "skapadDateTime": "2026-01-02T15:07:35.2285294",
      "uppdateradDateTime": "2026-01-02T15:08:15.9588433",
      "utkastId": null,
      "publicerad": true,
      "borttagen": false,
      "publiceradDateTime": "2026-01-02T15:08:15.9588432",
      "arkiverad": false,
      "historisk": false,
      "utkast": false
    },
    {
      "andringsforfattningId": 647685,
      "beteckning": "2025:1145",
      "anteckningar": "ändr. 16, 18, 19 §§",
      "ikraftDateTime": "2026-01-01T00:00:00",
      "ikraftOvergangsbestammelse": false,
      "ikraftDenDagenRegeringenBestammer": false,
      "forarbeten": null,
      "rubrik": "Förordning (2025:1145) om ändring i förordningen (2015:1053) om totalförsvar och höjd beredskap",
      "lopnummer": "1145",
      "celexnummer": null,
      "bihangsuppgifterTillAldreGrundforfattningar": null,
      "publiceringsar": "2025",
      "eUdirektiv": false,
      "skapadDateTime": "2026-01-02T15:07:35.2285296",
      "uppdateradDateTime": "2026-01-02T15:08:15.9588489",
      "utkastId": null,
      "publicerad": true,
      "borttagen": false,
      "publiceradDateTime": "2026-01-02T15:08:15.9588488",
      "arkiverad": false,
      "historisk": false,
      "utkast": false
    }
  ],
  "skapadDateTime": "2026-01-02T15:07:35.2133449",
  "uppdateradDateTime": "2026-01-02T15:08:15.9585098",
  "publicerad": true,
  "publiceradDateTime": "2026-01-02T15:08:15.9585097",
  "arkiverad": false,
  "historisk": false,
  "utkast": false,
  "dokumenttyp": "SFS"
}